{
  "4FursJXc3tQr08ZQSjp0": {
    "facilityName": "تجربة 1",
    "governorate": "المنيا",
    "accreditationStatus": "تجديد / استكمال اعتماد",
    "month": "2025-10",
    "year": 2025,
    "createdBy": "ttgaFvKjoDMZbnC2obeR3X0d2GZ2",
    "updatedBy": "ttgaFvKjoDMZbnC2obeR3X0d2GZ2",
    "createdAt": {
      "_seconds": 1765443168,
      "_nanoseconds": 37000000
    },
    "updatedAt": {
      "_seconds": 1765443168,
      "_nanoseconds": 37000000
    }
  },
  "91mJNKarx1haBuHHbdxD": {
    "facilityName": "تجربة 2",
    "governorate": "بورسعيد",
    "accreditationStatus": "تجديد / استكمال اعتماد",
    "month": "2025-10",
    "year": 2025,
    "createdBy": "ttgaFvKjoDMZbnC2obeR3X0d2GZ2",
    "updatedBy": "ttgaFvKjoDMZbnC2obeR3X0d2GZ2",
    "createdAt": {
      "_seconds": 1765443224,
      "_nanoseconds": 627000000
    },
    "updatedAt": {
      "_seconds": 1765443224,
      "_nanoseconds": 627000000
    }
  },
  "fd1lzc9R9qDYseU98wZo": {
    "facilityName": "تجربة",
    "governorate": "القاهرة",
    "accreditationStatus": "منشأة جديدة",
    "month": "2025-10",
    "year": 2025,
    "createdBy": "ttgaFvKjoDMZbnC2obeR3X0d2GZ2",
    "updatedBy": "ttgaFvKjoDMZbnC2obeR3X0d2GZ2",
    "createdAt": {
      "_seconds": 1765443150,
      "_nanoseconds": 270000000
    },
    "updatedAt": {
      "_seconds": 1765443150,
      "_nanoseconds": 270000000
    }
  },
  "lCmjYyfndm4hxrW0318T": {
    "facilityName": "تجربة 3",
    "governorate": "أسيوط",
    "accreditationStatus": "منشأة جديدة",
    "month": "2025-10",
    "year": 2025,
    "createdBy": "ttgaFvKjoDMZbnC2obeR3X0d2GZ2",
    "updatedBy": "ttgaFvKjoDMZbnC2obeR3X0d2GZ2",
    "createdAt": {
      "_seconds": 1765443389,
      "_nanoseconds": 61000000
    },
    "updatedAt": {
      "_seconds": 1765443389,
      "_nanoseconds": 61000000
    }
  }
}